tmtk/__init__.py
tmtk/options.py
tmtk/study.py
tmtk/version.py
tmtk/annotation/AnnotationBase.py
tmtk/annotation/Annotations.py
tmtk/annotation/ChromosomalRegions.py
tmtk/annotation/MicroarrayAnnotation.py
tmtk/annotation/MirnaAnnotation.py
tmtk/annotation/ProteomicsAnnotation.py
tmtk/annotation/__init__.py
tmtk/arborist/__init__.py
tmtk/arborist/common.py
tmtk/arborist/connect_to_baas.py
tmtk/arborist/jstreecontrol.py
tmtk/arborist/jupyter_extension.py
tmtk/arborist/static/bootstrap-4.0.0a5.css
tmtk/arborist/static/bootstrap-4.0.0a5.js
tmtk/arborist/static/favicon.ico
tmtk/arborist/static/jquery-1.11.1.js
tmtk/arborist/static/jupyter_embedded.html
tmtk/arborist/static/mainstyle.css
tmtk/arborist/static/placeholder.js
tmtk/arborist/static/tether-1.2.0.js
tmtk/arborist/static/tree.js
tmtk/arborist/static/images/add_tag.png
tmtk/arborist/static/images/addfolder.png
tmtk/arborist/static/images/folder.png
tmtk/arborist/static/images/helpicon.jpg
tmtk/arborist/static/images/pin.png
tmtk/arborist/static/images/screenshot.png
tmtk/arborist/static/images/spin.svg
tmtk/arborist/static/images/message/error.png
tmtk/arborist/static/images/message/info.png
tmtk/arborist/static/images/message/warning.png
tmtk/arborist/static/images/tree/alpha.gif
tmtk/arborist/static/images/tree/code.png
tmtk/arborist/static/images/tree/dna_icon.png
tmtk/arborist/static/images/tree/empty.png
tmtk/arborist/static/images/tree/folder.gif
tmtk/arborist/static/images/tree/green_info.png
tmtk/arborist/static/images/tree/numeric.gif
tmtk/arborist/static/images/tree/study.png
tmtk/arborist/static/images/tree/tag_icon.png
tmtk/arborist/static/jstree/dist/jstree.js
tmtk/arborist/static/jstree/dist/jstree.min.js
tmtk/arborist/static/jstree/dist/themes/default/32px.png
tmtk/arborist/static/jstree/dist/themes/default/40px.png
tmtk/arborist/static/jstree/dist/themes/default/style.css
tmtk/arborist/static/jstree/dist/themes/default/style.min.css
tmtk/arborist/static/jstree/dist/themes/default/throbber.gif
tmtk-0.5.8.dist-info/LICENSE.txt
tmtk-0.5.8.dist-info/METADATA
tmtk-0.5.8.dist-info/WHEEL
tmtk-0.5.8.dist-info/entry_points.txt
tmtk-0.5.8.dist-info/top_level.txt
tmtk-0.5.8.dist-info/RECORD
