Metadata-Version: 2.1
Name: tmtk
Version: 0.5.8
Summary: A toolkit for ETL curation for the tranSMART data warehouse.
Home-page: https://www.github.com/thehyve/tmtk/
Author: Jochem Bijlard
Author-email: j.bijlard@gmail.com
License: UNKNOWN
Download-URL: https://github.com/thehyve/tmtk/tarball/0.5.8/
Keywords: transmart,etl,arborist,concept tree
Platform: UNKNOWN
Classifier: Programming Language :: Python
Classifier: Programming Language :: Python :: 3
Classifier: Programming Language :: Python :: 3.5
Classifier: Programming Language :: Python :: 3.6
Classifier: Programming Language :: Python :: 3.7
Classifier: Programming Language :: Python :: 3.8
Requires-Dist: pandas (<0.26.0,>=0.22.0)
Requires-Dist: ipython (>=7.9.0)
Requires-Dist: jupyter (<1.1.0,>=1.0.0)
Requires-Dist: jupyter-client (>=5.3.4)
Requires-Dist: jupyter-core (<4.7.0,>=4.6.1)
Requires-Dist: jupyter-console (>=5.2.0)
Requires-Dist: notebook (<6.1.0,>=5.7.8)
Requires-Dist: requests (<2.23.0,>=2.22.0)
Requires-Dist: tqdm (>=4.40.0)
Requires-Dist: xlrd (>=1.2.0)
Requires-Dist: click (>=7.0)
Requires-Dist: arrow (>=0.15.4)
